odoo/addons/event_contact/README.rst
odoo/addons/event_contact/__init__.py
odoo/addons/event_contact/__manifest__.py
odoo/addons/event_contact/i18n/es.po
odoo/addons/event_contact/i18n/event_contact.pot
odoo/addons/event_contact/i18n/it.po
odoo/addons/event_contact/i18n/sv.po
odoo/addons/event_contact/models/__init__.py
odoo/addons/event_contact/models/event_event.py
odoo/addons/event_contact/models/event_type.py
odoo/addons/event_contact/readme/CONTRIBUTORS.md
odoo/addons/event_contact/readme/DESCRIPTION.md
odoo/addons/event_contact/readme/USAGE.md
odoo/addons/event_contact/static/description/icon.png
odoo/addons/event_contact/static/description/index.html
odoo/addons/event_contact/tests/__init__.py
odoo/addons/event_contact/tests/test_event.py
odoo/addons/event_contact/views/event_event_view.xml
odoo/addons/event_contact/views/event_type_view.xml
odoo_addon_event_contact-18.0.1.0.1.1.dist-info/METADATA
odoo_addon_event_contact-18.0.1.0.1.1.dist-info/WHEEL
odoo_addon_event_contact-18.0.1.0.1.1.dist-info/top_level.txt
odoo_addon_event_contact-18.0.1.0.1.1.dist-info/RECORD
