Metadata-Version: 2.1
Name: odoo-addon-event_contact
Version: 18.0.1.0.1.1
Requires-Python: >=3.10
Requires-Dist: odoo==18.0.*
Summary: Add contacts to event and event type
Home-page: https://github.com/OCA/event
License: AGPL-3
Author: OpenSynergy Indonesia, Tecnativa, Odoo Community Association (OCA)
Author-email: support@odoo-community.org
Classifier: Programming Language :: Python
Classifier: Framework :: Odoo
Classifier: Framework :: Odoo :: 18.0
Classifier: License :: OSI Approved :: GNU Affero General Public License v3
